country/__init__.py
country/countryLib.py
countryLib-0.0.2.dist-info/METADATA
countryLib-0.0.2.dist-info/WHEEL
countryLib-0.0.2.dist-info/top_level.txt
countryLib-0.0.2.dist-info/RECORD
